LICENSE
MANIFEST.in
README.md
README.rst
setup.py
segment_liftover/__init__.py
segment_liftover/segmentLiftover.py
segment_liftover.egg-info/PKG-INFO
segment_liftover.egg-info/SOURCES.txt
segment_liftover.egg-info/dependency_links.txt
segment_liftover.egg-info/entry_points.txt
segment_liftover.egg-info/requires.txt
segment_liftover.egg-info/top_level.txt
segment_liftover/chains/hg18ToHg19.over.chain.gz
segment_liftover/chains/hg18ToHg38.over.chain.gz
segment_liftover/chains/hg19ToHg18.over.chain.gz
segment_liftover/chains/hg19ToHg38.over.chain.gz
segment_liftover/chains/hg38ToHg19.over.chain.gz
segment_liftover/examples/sample_1/probes.tsv
segment_liftover/examples/sample_1/segments.tsv
segment_liftover/examples/sample_2/probes.tsv
segment_liftover/examples/sample_2/segments.tsv
segment_liftover/examples/sample_3/probes.tsv
segment_liftover/examples/sample_3/segments.tsv