Metadata-Version: 1.2
Name: segment-liftover
Version: 0.956
Summary: Convert segments between genomic assemblies in whole.
Home-page: https://github.com/baudisgroup/segment-liftover
Author: Bo Gao
Author-email: kaye_gao@hotmail.com
License: MIT
Keywords: segment probe genome coordinate liftover
Platform: UNKNOWN
Classifier: Development Status :: 3 - Alpha
Classifier: Intended Audience :: Science/Research
Classifier: License :: OSI Approved :: MIT License
Classifier: Programming Language :: Python :: 3.6
Classifier: Topic :: Scientific/Engineering :: Bio-Informatics
Requires-Python: >=3.6
